uvabot/__init__.py
uvabot/account.py
uvabot/tradier.py
uvabot-0.0.3.dist-info/LICENSE
uvabot-0.0.3.dist-info/METADATA
uvabot-0.0.3.dist-info/WHEEL
uvabot-0.0.3.dist-info/top_level.txt
uvabot-0.0.3.dist-info/RECORD
