Metadata-Version: 2.1
Name: uvabot
Version: 0.0.3
Summary: Wrapper for Tradier API
Home-page: https://github.com/thammo4/tradier
Author: Tom Hammons
Author-email: qje5vf@virginia.edu
License: Apache-2.0
Requires-Python: >=3.6
License-File: LICENSE
Requires-Dist: requests (>=2.25.1)
Requires-Dist: pandas (>=1.2.4)
